catscan/__init__.py
catscan/__main__.py
catscan/config.py
catscan/exceptions.py
catscan/main.py
catscan/api/__init__.py
catscan/api/client.py
catscan/api/rate_limiter.py
catscan/api/terraform.py
catscan/auth/__init__.py
catscan/auth/config_auth.py
catscan/auth/keyring_auth.py
catscan/auth/validators.py
catscan/scanner/__init__.py
catscan/scanner/resources.py
catscan/scanner/state.py
catscan/scanner/workspace.py
catscan/storage/__init__.py
catscan/storage/config.py
catscan/storage/history.py
catscan/ui/__init__.py
catscan/ui/console.py
catscan/ui/curses_ui.py
catscan/ui/menus.py
catscan/ui/panels.py
catscan/ui/rich_ui.py
catscan/ui/tables.py
catscan/utils/__init__.py
catscan/utils/keyboard.py
catscan/utils/logging.py
catscan/utils/platform.py
catscan_terra-2.0.0.dist-info/METADATA
catscan_terra-2.0.0.dist-info/WHEEL
catscan_terra-2.0.0.dist-info/entry_points.txt
catscan_terra-2.0.0.dist-info/top_level.txt
catscan_terra-2.0.0.dist-info/RECORD
