Metadata-Version: 2.4
Name: catscan-terra
Version: 2.0.0
Summary: CatSCAN: Terraform Cloud multi-workspace scanner. Secure observability tool for your organization's workspaces.
Author-email: Simon Farrell <simon81farrell@gmail.com>
Project-URL: Homepage, https://github.com/cloudsifar/catscan-2.0
Project-URL: Bug Reports, https://github.com/cloudsifar/catscan-2.0/issues
Project-URL: Source, https://github.com/cloudsifar/catscan-2.0
Keywords: terraform,terraform-cloud,infrastructure,scanner,devops,cloud
Classifier: Development Status :: 4 - Beta
Classifier: Environment :: Console
Classifier: Intended Audience :: Developers
Classifier: Intended Audience :: System Administrators
Classifier: License :: OSI Approved :: MIT License
Classifier: Operating System :: OS Independent
Classifier: Programming Language :: Python :: 3
Classifier: Programming Language :: Python :: 3.9
Classifier: Programming Language :: Python :: 3.10
Classifier: Programming Language :: Python :: 3.11
Classifier: Topic :: System :: Systems Administration
Classifier: Topic :: Software Development :: Libraries :: Python Modules
Requires-Python: >=3.9
Requires-Dist: requests>=2.28.0
Requires-Dist: rich>=13.0
Requires-Dist: keyring>=24.0.0
Dynamic: requires-python
